[
  {
    "page": 84,
    "questions": [
      {
        "number": 84,
        "stem": "Examine a tabela.\nPorcentagem da variação do desempenho\neconômico do Brasil",
        "options": [],
        "bbox": {
          "x": 71,
          "y": 91,
          "w": 429,
          "h": 101
        }
      },
      {
        "number": 84,
        "stem": "Os dados da tabela referem-se a anos transcorridos durante a\nDitadura Militar no Brasil. O desempenho econômico nesse\nperíodo entrelaçou-se ao panorama político do país. Nesse\nsentido, é correto afirmar:",
        "options": [
          {
            "key": "A",
            "text": "Os sinais de esgotamento do \"milagre brasileiro\",\nassociados à crise internacional do petróleo entre 1973 e\n1974, foram os responsáveis pelo recrudescimento da\npolítica repressiva dos governos militares."
          },
          {
            "key": "B",
            "text": "As eleições pluripartidárias de 1982 ocorreram em meio à\nrecessão de 1981 e 1983, no governo de João Baptista\nFigueiredo, e caracterizaram-se como um passo importante\nno processo de democratização do país."
          },
          {
            "key": "C",
            "text": "A crise internacional do petróleo de 1979 e seus efeitos na\neconomia brasileira provocaram uma queda abrupta no PIB\nnacional e o fim imediato do regime, por falta de\nsustentação política."
          },
          {
            "key": "D",
            "text": "As oscilações do PIB brasileiro, registradas na tabela,\ncorrespondem igualmente às variações das taxas de\ncrescimento e retração na indústria e na agricultura e aos\nprocessos de intensificação da repressão política e da\ncensura."
          },
          {
            "key": "E",
            "text": "A crise internacional do petróleo de 1979 não afetou a\nagricultura brasileira, mas coincidiu com as primeiras\neleições pluripartidárias desde 1966, marcadas pela\nestrondosa vitória dos partidos de oposição."
          }
        ],
        "bbox": {
          "x": 71,
          "y": 428,
          "w": 429,
          "h": 368
        }
      },
      {
        "number": 85,
        "stem": "Sob qualquer aspecto, este [a Revolução Industrial] foi\nprovavelmente o mais importante acontecimento na história do\nmundo, pelo menos desde a invenção da agricultura e das\ncidades. E foi iniciado pela Grã-Bretanha. É evidente que isto\nnão foi acidental.\nEric Hobsbawm, A Era das Revoluções. São Paulo: Paz e Terra, 2005.\n19ª edição, p. 52.\nA Revolução Industrial, ocorrida na Inglaterra nos decênios\nfinais do século XVIII,",
        "options": [
          {
            "key": "A",
            "text": "deveu-se ao pioneirismo científico e tecnológico dos\nbritânicos, aliado a uma grande oferta de mão de obra\nespecializada e a uma política estatal pacifista e voltada\npara o comércio."
          },
          {
            "key": "B",
            "text": "originou-se das profundas transformações agrárias\nexpressas pela concentração fundiária, perda da posse da\nterra pelo campesinato e formação de uma mão de obra\nassalariada."
          },
          {
            "key": "C",
            "text": "vinculou-se à derrocada da aristocracia e à ascensão da\nburguesia, orientada pela política mercantilista e\nsintetizada na filosofia de Adam Smith."
          },
          {
            "key": "D",
            "text": "resultou da supressão de leis protecionistas de inspiração\nmercantilista e do combate ao tráfico negreiro, com vistas à\nconquista de mercados externos consumidores."
          },
          {
            "key": "E",
            "text": "decorreu da ampla difusão de um ideário Ilustrado, o qual\nteria promovido aquilo que o sociólogo alemão Max Weber\ndescreve como o \"espírito do capitalismo\"."
          }
        ],
        "bbox": {
          "x": 518,
          "y": 91,
          "w": 422,
          "h": 468
        }
      },
      {
        "number": 86,
        "stem": "Décio Villares, A República (Museu Republicano, RJ, ca 1900)\nProduzida no contexto da implantação da ordem republicana\nno Brasil, esta imagem",
        "options": [
          {
            "key": "A",
            "text": "caracteriza representação cívica inspirada na Revolução\nFrancesa, adequada ao projeto democrático estabelecido\npelos republicanos brasileiros."
          },
          {
            "key": "B",
            "text": "faz uso alegórico de um tema clássico para expressar o\nrepúdio à exclusão da participação feminina nas instituições\npolíticas do Império."
          },
          {
            "key": "C",
            "text": "é uma alegoria da liberdade, da pátria e da nação, que\ncontrasta com os limites da cidadania na nova ordem\nbrasileira."
          },
          {
            "key": "D",
            "text": "emprega símbolo católico como estratégia para obter a\nadesão da Igreja e diminuir a animosidade dos movimentos\nmessiânicos."
          },
          {
            "key": "E",
            "text": "é expressão artística do projeto positivista de divulgar uma\nconcepção da sociedade brasileira sintonizada com os ideais\nde eugenia."
          }
        ],
        "bbox": {
          "x": 518,
          "y": 578,
          "w": 422,
          "h": 272
        }
      }
    ]
  }
]